bloic/__init__.py
bloic/__main__.py
bloic/_version.py
bloic/entrypoint.py
bloic-1.1.0.dist-info/LICENSE
bloic-1.1.0.dist-info/METADATA
bloic-1.1.0.dist-info/WHEEL
bloic-1.1.0.dist-info/entry_points.txt
bloic-1.1.0.dist-info/top_level.txt
bloic-1.1.0.dist-info/RECORD
